PymiliZip/__init__.py
PymiliZip/milizip.py
PymiliZip-0.0.1.dist-info/LICENSE.txt
PymiliZip-0.0.1.dist-info/METADATA
PymiliZip-0.0.1.dist-info/WHEEL
PymiliZip-0.0.1.dist-info/top_level.txt
PymiliZip-0.0.1.dist-info/RECORD
